[
    {
        "location": "新北中和店",
        "year": "2020",
        "brand": "台鈴",
        "shopee_code": "1147069",
        "ruten_code": "0019000200020003",
        "model": "SALUTO 125",
        "tag": "#8319",
        "condition": "檢查和更換耗材，確保車輛運作順暢",
        "mileage": "8,XXX km",
        "images": [
            "https://cdn.store-assets.com/s/1336053/i/85249489.jpeg",
            "https://cdn.store-assets.com/s/1336053/i/85249490.jpeg",
            "https://cdn.store-assets.com/s/1336053/i/85249487.jpeg",
            "https://cdn.store-assets.com/s/1336053/i/85249491.jpeg",
            "https://cdn.store-assets.com/s/1336053/i/85249488.jpeg"
        ],
        "price": "5200000",
        "warranty": true
    },
    {
        "location": "新北中和店",
        "year": "2021",
        "brand": "光陽",
        "shopee_code": "1095314",
        "ruten_code": "0019000200020001",
        "model": "KRV 180",
        "tag": "#2888",
        "condition": "檢查和更換耗材，確保車輛運作順暢",
        "mileage": "5,XXX km",
        "images": [
            "https://cdn.store-assets.com/s/1336053/i/85249200.jpeg",
            "https://cdn.store-assets.com/s/1336053/i/85249197.jpeg",
            "https://cdn.store-assets.com/s/1336053/i/85249201.jpeg",
            "https://cdn.store-assets.com/s/1336053/i/85249198.jpeg",
            "https://cdn.store-assets.com/s/1336053/i/85249199.jpeg"
        ],
        "price": "6999900",
        "warranty": true
    },
    {
        "location": "新北中和店",
        "year": "2021",
        "brand": "山葉",
        "shopee_code": "1802940",
        "ruten_code": "0019000200020006",
        "model": "BWS 125 水冷",
        "tag": "#1231",
        "condition": "檢查和更換耗材，確保車輛運作順暢",
        "mileage": "24,XXX km",
        "images": [
            "https://cdn.store-assets.com/s/1336053/i/85248226.jpeg",
            "https://cdn.store-assets.com/s/1336053/i/85248227.jpeg",
            "https://cdn.store-assets.com/s/1336053/i/85248224.jpeg",
            "https://cdn.store-assets.com/s/1336053/i/85248228.jpeg",
            "https://cdn.store-assets.com/s/1336053/i/85248225.jpeg"
        ],
        "price": "6500000",
        "warranty": true
    },
    {
        "location": "新北中和店",
        "year": "2022",
        "brand": "三陽",
        "shopee_code": "1107843",
        "ruten_code": "0019000200020004",
        "model": "全新迪爵 碟煞 CBS",
        "tag": "#0007",
        "condition": "檢查和更換耗材，確保車輛運作順暢",
        "mileage": "8,XXX km",
        "images": [
            "https://cdn.store-assets.com/s/1336053/i/85247105.jpeg",
            "https://cdn.store-assets.com/s/1336053/i/85247102.jpeg",
            "https://cdn.store-assets.com/s/1336053/i/85247104.jpeg",
            "https://cdn.store-assets.com/s/1336053/i/85247103.jpeg",
            "https://cdn.store-assets.com/s/1336053/i/85247101.jpeg"
        ],
        "price": "5200000",
        "warranty": true
    },
    {
        "location": "新北中和店",
        "year": "2020",
        "brand": "三陽",
        "shopee_code": "1107843",
        "ruten_code": "0019000200020004",
        "model": "DRG 158 ABS 六期",
        "tag": "#8528",
        "condition": "檢查和更換耗材，確保車輛運作順暢",
        "mileage": "39,XXX km",
        "images": [
            "https://cdn.store-assets.com/s/1336053/i/85246805.jpeg",
            "https://cdn.store-assets.com/s/1336053/i/85246808.jpeg",
            "https://cdn.store-assets.com/s/1336053/i/85246804.jpeg",
            "https://cdn.store-assets.com/s/1336053/i/85246806.jpeg",
            "https://cdn.store-assets.com/s/1336053/i/85246809.jpeg"
        ],
        "price": "5999900",
        "warranty": true
    },
    {
        "location": "新北中和店",
        "year": "2019",
        "brand": "三陽",
        "shopee_code": "1107843",
        "ruten_code": "0019000200020004",
        "model": "DRG 158 ABS 六期",
        "tag": "#1678",
        "condition": "檢查和更換耗材，確保車輛運作順暢",
        "mileage": "32,XXX km",
        "images": [
            "https://cdn.store-assets.com/s/1336053/i/85246214.jpeg",
            "https://cdn.store-assets.com/s/1336053/i/85246216.jpeg",
            "https://cdn.store-assets.com/s/1336053/i/85246218.jpeg",
            "https://cdn.store-assets.com/s/1336053/i/85246215.jpeg",
            "https://cdn.store-assets.com/s/1336053/i/85246217.jpeg"
        ],
        "price": "5800000",
        "warranty": true
    },
    {
        "location": "新北中和店",
        "year": "2017",
        "brand": "光陽",
        "shopee_code": "1095314",
        "ruten_code": "0019000200020001",
        "model": "G6 150",
        "tag": "#2672",
        "condition": "檢查和更換耗材，確保車輛運作順暢",
        "mileage": "32,XXX km",
        "images": [
            "https://cdn.store-assets.com/s/1336053/i/85245991.jpeg",
            "https://cdn.store-assets.com/s/1336053/i/85245989.jpeg",
            "https://cdn.store-assets.com/s/1336053/i/85245988.jpeg",
            "https://cdn.store-assets.com/s/1336053/i/85245987.jpeg",
            "https://cdn.store-assets.com/s/1336053/i/85245990.jpeg"
        ],
        "price": "3600000",
        "warranty": true
    },
    {
        "location": "新北中和店",
        "year": "2021",
        "brand": "山葉",
        "shopee_code": "1802940",
        "ruten_code": "0019000200020006",
        "model": "MT-15 金倒叉",
        "tag": "#2887",
        "condition": "檢查和更換耗材，確保車輛運作順暢",
        "mileage": "28,XXX km",
        "images": [
            "https://cdn.store-assets.com/s/1336053/i/85245797.jpeg",
            "https://cdn.store-assets.com/s/1336053/i/85245798.jpeg",
            "https://cdn.store-assets.com/s/1336053/i/85245800.jpeg",
            "https://cdn.store-assets.com/s/1336053/i/85245799.jpeg",
            "https://cdn.store-assets.com/s/1336053/i/85245796.jpeg"
        ],
        "price": "7200000",
        "warranty": false
    },
    {
        "location": "桃園中壢店",
        "year": "2024",
        "brand": "三陽",
        "shopee_code": "1107843",
        "ruten_code": "0019000200020004",
        "model": "CLBCU 125 CBS",
        "tag": "#9955",
        "condition": "檢查和更換耗材，確保車輛運作順暢",
        "mileage": "5,XXX km",
        "images": [
            "https://cdn.store-assets.com/s/1336053/i/85243257.jpeg",
            "https://cdn.store-assets.com/s/1336053/i/85243259.jpeg",
            "https://cdn.store-assets.com/s/1336053/i/85243258.jpeg",
            "https://cdn.store-assets.com/s/1336053/i/85243260.jpeg",
            "https://cdn.store-assets.com/s/1336053/i/85243261.jpeg"
        ],
        "price": "6999900",
        "warranty": true
    },
    {
        "location": "新北樹林店",
        "year": "2024",
        "brand": "三陽",
        "shopee_code": "1107843",
        "ruten_code": "0019000200020004",
        "model": "JETS SL 158",
        "tag": "#5929",
        "condition": "檢查和更換耗材，確保車輛運作順暢",
        "mileage": "15,XXX km",
        "images": [
            "https://cdn.store-assets.com/s/1336053/i/85238331.jpeg",
            "https://cdn.store-assets.com/s/1336053/i/85238332.jpeg",
            "https://cdn.store-assets.com/s/1336053/i/85238336.jpeg",
            "https://cdn.store-assets.com/s/1336053/i/85238330.jpeg",
            "https://cdn.store-assets.com/s/1336053/i/85238334.jpeg"
        ],
        "price": "9200000",
        "warranty": true
    },
    {
        "location": "台中旗艦店",
        "year": "2021",
        "brand": "山葉",
        "shopee_code": "1802940",
        "ruten_code": "0019000200020006",
        "model": "FORCE 155",
        "tag": "#8701",
        "condition": "檢查和更換耗材，確保車輛運作順暢",
        "mileage": "17,XXX km",
        "images": [
            "https://cdn.store-assets.com/s/1336053/i/85238613.jpeg",
            "https://cdn.store-assets.com/s/1336053/i/85238616.jpeg",
            "https://cdn.store-assets.com/s/1336053/i/85238624.jpeg",
            "https://cdn.store-assets.com/s/1336053/i/85238635.jpeg",
            "https://cdn.store-assets.com/s/1336053/i/85238637.jpeg"
        ],
        "price": "5999900",
        "warranty": true
    },
    {
        "location": "台中旗艦店",
        "year": "2021",
        "brand": "山葉",
        "shopee_code": "1802940",
        "ruten_code": "0019000200020006",
        "model": "R15 V3 正叉",
        "tag": "#1393",
        "condition": "檢查和更換耗材，確保車輛運作順暢",
        "mileage": "3,XXX km",
        "images": [
            "https://cdn.store-assets.com/s/1336053/i/85218096.jpeg",
            "https://cdn.store-assets.com/s/1336053/i/85218098.jpeg",
            "https://cdn.store-assets.com/s/1336053/i/85218099.jpeg",
            "https://cdn.store-assets.com/s/1336053/i/85218101.jpeg",
            "https://cdn.store-assets.com/s/1336053/i/85218102.jpeg"
        ],
        "price": "6800000",
        "warranty": false
    },
    {
        "location": "台中旗艦店",
        "year": "2016",
        "brand": "山葉",
        "shopee_code": "1802940",
        "ruten_code": "0019000200020006",
        "model": "勁戰四代125",
        "tag": "#6536",
        "condition": "檢查和更換耗材，確保車輛運作順暢",
        "mileage": "19,XXX km",
        "images": [
            "https://cdn.store-assets.com/s/1336053/i/85218020.jpeg",
            "https://cdn.store-assets.com/s/1336053/i/85218022.jpeg",
            "https://cdn.store-assets.com/s/1336053/i/85218028.jpeg",
            "https://cdn.store-assets.com/s/1336053/i/85218030.jpeg",
            "https://cdn.store-assets.com/s/1336053/i/85218032.jpeg"
        ],
        "price": "4200000",
        "warranty": true
    }
]