[
    {
        "location": "新北中和店",
        "year": "2014",
        "brand": "光陽",
        "shopee_code": "1095314",
        "ruten_code": "0019000200020001",
        "model": "光陽 MANY 110",
        "tag": "#297",
        "condition": "檢查和更換耗材，確保車輛運作順暢",
        "mileage": "26,XXX km",
        "images": [
            "https://cdn.store-assets.com/s/1336053/i/87359566.jpeg",
            "https://cdn.store-assets.com/s/1336053/i/87359564.jpeg",
            "https://cdn.store-assets.com/s/1336053/i/87359565.jpeg",
            "https://cdn.store-assets.com/s/1336053/i/87359568.jpeg",
            "https://cdn.store-assets.com/s/1336053/i/87359567.jpeg"
        ],
        "price": "33000",
        "warranty": true
    },
    {
        "location": "桃園中壢店",
        "year": "2021",
        "brand": "三陽",
        "shopee_code": "1107843",
        "ruten_code": "0019000200020004",
        "model": "三陽 野狼傳奇 125 循環檔",
        "tag": "#0119",
        "condition": "檢查和更換耗材，確保車輛運作順暢",
        "mileage": "1,XXX km",
        "images": [
            "https://cdn.store-assets.com/s/1336053/i/87360626.jpeg",
            "https://cdn.store-assets.com/s/1336053/i/87360627.jpeg",
            "https://cdn.store-assets.com/s/1336053/i/87360630.jpeg",
            "https://cdn.store-assets.com/s/1336053/i/87360629.jpeg",
            "https://cdn.store-assets.com/s/1336053/i/87360628.jpeg"
        ],
        "price": "55000",
        "warranty": true
    },
    {
        "location": "桃園中壢店",
        "year": "2007",
        "brand": "三陽",
        "shopee_code": "1107843",
        "ruten_code": "0019000200020004",
        "model": "三陽 WOWWOW 100 循環檔",
        "tag": "#8601",
        "condition": "檢查和更換耗材，確保車輛運作順暢",
        "mileage": "15,XXX km",
        "images": [
            "https://cdn.store-assets.com/s/1336053/i/87360507.jpeg",
            "https://cdn.store-assets.com/s/1336053/i/87360508.jpeg",
            "https://cdn.store-assets.com/s/1336053/i/87360509.jpeg",
            "https://cdn.store-assets.com/s/1336053/i/87360510.jpeg",
            "https://cdn.store-assets.com/s/1336053/i/87360511.jpeg"
        ],
        "price": "39999",
        "warranty": true
    },
    {
        "location": "桃園中壢店",
        "year": "2022",
        "brand": "山葉",
        "shopee_code": "1802940",
        "ruten_code": "0019000200020006",
        "model": "山葉 勁戰六代 ABS",
        "tag": "#2595",
        "condition": "檢查和更換耗材，確保車輛運作順暢",
        "mileage": "9,XXX km",
        "images": [
            "https://cdn.store-assets.com/s/1336053/i/87360093.jpeg",
            "https://cdn.store-assets.com/s/1336053/i/87360095.jpeg",
            "https://cdn.store-assets.com/s/1336053/i/87360094.jpeg",
            "https://cdn.store-assets.com/s/1336053/i/87360097.jpeg",
            "https://cdn.store-assets.com/s/1336053/i/87360096.jpeg"
        ],
        "price": "69999",
        "warranty": true
    },
    {
        "location": "新北樹林店",
        "year": "2016",
        "brand": "PGO",
        "shopee_code": "1101057",
        "ruten_code": "0019000200020002",
        "model": "PGO BON 125 ABS",
        "tag": "#3595",
        "condition": "檢查和更換耗材，確保車輛運作順暢",
        "mileage": "22,XXX km",
        "images": [
            "https://cdn.store-assets.com/s/1336053/i/87375153.jpeg",
            "https://cdn.store-assets.com/s/1336053/i/87375149.jpeg",
            "https://cdn.store-assets.com/s/1336053/i/87375150.jpeg",
            "https://cdn.store-assets.com/s/1336053/i/87375152.jpeg",
            "https://cdn.store-assets.com/s/1336053/i/87375151.jpeg"
        ],
        "price": "35000",
        "warranty": true
    },
    {
        "location": "新北樹林店",
        "year": "2020",
        "brand": "山葉",
        "shopee_code": "1802940",
        "ruten_code": "0019000200020006",
        "model": "山葉 R15 V3 倒叉",
        "tag": "#6511",
        "condition": "檢查和更換耗材，確保車輛運作順暢",
        "mileage": "29,XXX km",
        "images": [
            "https://cdn.store-assets.com/s/1336053/i/87373734.jpeg",
            "https://cdn.store-assets.com/s/1336053/i/87373737.jpeg",
            "https://cdn.store-assets.com/s/1336053/i/87373738.jpeg",
            "https://cdn.store-assets.com/s/1336053/i/87373736.jpeg",
            "https://cdn.store-assets.com/s/1336053/i/87373735.jpeg"
        ],
        "price": "59999",
        "warranty": false
    },
    {
        "location": "高雄鳳山店",
        "year": "2020",
        "brand": "三陽",
        "shopee_code": "1107843",
        "ruten_code": "0019000200020004",
        "model": "三陽 Woo 115 CBS",
        "tag": "#5368",
        "condition": "檢查和更換耗材，確保車輛運作順暢",
        "mileage": "41,XXX km",
        "images": [
            "https://cdn.store-assets.com/s/1336053/i/87377498.jpeg",
            "https://cdn.store-assets.com/s/1336053/i/87377502.jpeg",
            "https://cdn.store-assets.com/s/1336053/i/87377499.jpeg",
            "https://cdn.store-assets.com/s/1336053/i/87377501.jpeg",
            "https://cdn.store-assets.com/s/1336053/i/87377505.jpeg",
            "https://cdn.store-assets.com/s/1336053/i/87377504.jpeg",
            "https://cdn.store-assets.com/s/1336053/i/87377493.jpeg",
            "https://cdn.store-assets.com/s/1336053/i/87377494.jpeg"
        ],
        "price": "32000",
        "warranty": true
    },
    {
        "location": "高雄鳳山店",
        "year": "2024",
        "brand": "三陽",
        "shopee_code": "1107843",
        "ruten_code": "0019000200020004",
        "model": "三陽 JET SL+ 158 TCS",
        "tag": "#8299",
        "condition": "檢查和更換耗材，確保車輛運作順暢",
        "mileage": "9,XXX km",
        "images": [
            "https://cdn.store-assets.com/s/1336053/i/87371367.jpeg",
            "https://cdn.store-assets.com/s/1336053/i/87371368.jpeg",
            "https://cdn.store-assets.com/s/1336053/i/87371369.jpeg",
            "https://cdn.store-assets.com/s/1336053/i/87371370.jpeg",
            "https://cdn.store-assets.com/s/1336053/i/87371371.jpeg",
            "https://cdn.store-assets.com/s/1336053/i/87371372.jpeg",
            "https://cdn.store-assets.com/s/1336053/i/87371360.jpeg",
            "https://cdn.store-assets.com/s/1336053/i/87371359.jpeg",
            "https://cdn.store-assets.com/s/1336053/i/87371361.jpeg",
            "https://cdn.store-assets.com/s/1336053/i/87371362.jpeg",
            "https://cdn.store-assets.com/s/1336053/i/87371364.jpeg",
            "https://cdn.store-assets.com/s/1336053/i/87371365.jpeg",
            "https://cdn.store-assets.com/s/1336053/i/87371363.jpeg",
            "https://cdn.store-assets.com/s/1336053/i/87371366.jpeg"
        ],
        "price": "95000",
        "warranty": true
    },
    {
        "location": "高雄鳳山店",
        "year": "2024",
        "brand": "光陽",
        "shopee_code": "1095314",
        "ruten_code": "0019000200020001",
        "model": "光陽 I-Many 110",
        "tag": "#2693",
        "condition": "檢查和更換耗材，確保車輛運作順暢",
        "mileage": "3,9XX km",
        "images": [
            "https://cdn.store-assets.com/s/1336053/i/87370568.jpeg",
            "https://cdn.store-assets.com/s/1336053/i/87370571.jpeg",
            "https://cdn.store-assets.com/s/1336053/i/87370569.jpeg",
            "https://cdn.store-assets.com/s/1336053/i/87370570.jpeg",
            "https://cdn.store-assets.com/s/1336053/i/87370573.jpeg",
            "https://cdn.store-assets.com/s/1336053/i/87370572.jpeg",
            "https://cdn.store-assets.com/s/1336053/i/87370567.jpeg"
        ],
        "price": "62000",
        "warranty": true
    },
    {
        "location": "高雄鳳山店",
        "year": "2022",
        "brand": "本田",
        "shopee_code": "1146583",
        "ruten_code": "0019000200020008",
        "model": "本田 Hornet 2.0",
        "tag": "#9703",
        "condition": "檢查和更換耗材，確保車輛運作順暢",
        "mileage": "5,2XX km",
        "images": [
            "https://cdn.store-assets.com/s/1336053/i/87370099.jpeg",
            "https://cdn.store-assets.com/s/1336053/i/87370100.jpeg",
            "https://cdn.store-assets.com/s/1336053/i/87370101.jpeg",
            "https://cdn.store-assets.com/s/1336053/i/87370102.jpeg",
            "https://cdn.store-assets.com/s/1336053/i/87370104.jpeg",
            "https://cdn.store-assets.com/s/1336053/i/87370103.jpeg"
        ],
        "price": "75000",
        "warranty": true
    },
    {
        "location": "高雄鳳山店",
        "year": "2021",
        "brand": "三陽",
        "shopee_code": "1107843",
        "ruten_code": "0019000200020004",
        "model": "三陽 野狼125",
        "tag": "#2165",
        "condition": "檢查和更換耗材，確保車輛運作順暢",
        "mileage": "14,XXX km",
        "images": [
            "https://cdn.store-assets.com/s/1336053/i/87369659.jpeg",
            "https://cdn.store-assets.com/s/1336053/i/87369658.jpeg",
            "https://cdn.store-assets.com/s/1336053/i/87369657.jpeg",
            "https://cdn.store-assets.com/s/1336053/i/87369661.jpeg",
            "https://cdn.store-assets.com/s/1336053/i/87369660.jpeg",
            "https://cdn.store-assets.com/s/1336053/i/87369656.jpeg",
            "https://cdn.store-assets.com/s/1336053/i/87369653.jpeg",
            "https://cdn.store-assets.com/s/1336053/i/87369655.jpeg",
            "https://cdn.store-assets.com/s/1336053/i/87369654.jpeg"
        ],
        "price": "48000",
        "warranty": true
    },
    {
        "location": "高雄鳳山店",
        "year": "2019",
        "brand": "台鈴",
        "shopee_code": "1147069",
        "ruten_code": "0019000200020003",
        "model": "台鈴 GSX-R 150 ABS",
        "tag": "#3832",
        "condition": "檢查和更換耗材，確保車輛運作順暢",
        "mileage": "14,XXX km",
        "images": [
            "https://cdn.store-assets.com/s/1336053/i/87368952.jpeg",
            "https://cdn.store-assets.com/s/1336053/i/87368949.jpeg",
            "https://cdn.store-assets.com/s/1336053/i/87368950.jpeg",
            "https://cdn.store-assets.com/s/1336053/i/87368953.jpeg",
            "https://cdn.store-assets.com/s/1336053/i/87368954.jpeg",
            "https://cdn.store-assets.com/s/1336053/i/87368951.jpeg",
            "https://cdn.store-assets.com/s/1336053/i/87368945.jpeg",
            "https://cdn.store-assets.com/s/1336053/i/87368947.jpeg",
            "https://cdn.store-assets.com/s/1336053/i/87368948.jpeg",
            "https://cdn.store-assets.com/s/1336053/i/87368944.jpeg",
            "https://cdn.store-assets.com/s/1336053/i/87368943.jpeg",
            "https://cdn.store-assets.com/s/1336053/i/87368946.jpeg"
        ],
        "price": "52000",
        "warranty": true
    },
    {
        "location": "高雄鳳山店",
        "year": "2014",
        "brand": "2014",
        "shopee_code": "999999",
        "ruten_code": "9999999999999999",
        "model": "MANY 110",
        "tag": "#088",
        "condition": "檢查和更換耗材，確保車輛運作順暢",
        "mileage": "46,XXX km",
        "images": [
            "https://cdn.store-assets.com/s/1336053/i/87366307.jpeg",
            "https://cdn.store-assets.com/s/1336053/i/87366305.jpeg",
            "https://cdn.store-assets.com/s/1336053/i/87366303.jpeg",
            "https://cdn.store-assets.com/s/1336053/i/87366306.jpeg",
            "https://cdn.store-assets.com/s/1336053/i/87366308.jpeg",
            "https://cdn.store-assets.com/s/1336053/i/87366304.jpeg",
            "https://cdn.store-assets.com/s/1336053/i/87366309.jpeg",
            "https://cdn.store-assets.com/s/1336053/i/87366301.jpeg",
            "https://cdn.store-assets.com/s/1336053/i/87366300.jpeg",
            "https://cdn.store-assets.com/s/1336053/i/87366302.jpeg",
            "https://cdn.store-assets.com/s/1336053/i/87366298.jpeg",
            "https://cdn.store-assets.com/s/1336053/i/87366299.jpeg",
            "https://cdn.store-assets.com/s/1336053/i/87366297.jpeg"
        ],
        "price": "35000",
        "warranty": true
    },
    {
        "location": "高雄鳳山店",
        "year": "2024",
        "brand": "光陽",
        "shopee_code": "1095314",
        "ruten_code": "0019000200020001",
        "model": "光陽 K1 125",
        "tag": "#0138",
        "condition": "檢查和更換耗材，確保車輛運作順暢",
        "mileage": "3,8XX km",
        "images": [
            "https://cdn.store-assets.com/s/1336053/i/87365930.jpeg",
            "https://cdn.store-assets.com/s/1336053/i/87365931.jpeg",
            "https://cdn.store-assets.com/s/1336053/i/87365932.jpeg",
            "https://cdn.store-assets.com/s/1336053/i/87365933.jpeg",
            "https://cdn.store-assets.com/s/1336053/i/87365935.jpeg",
            "https://cdn.store-assets.com/s/1336053/i/87365934.jpeg"
        ],
        "price": "58000",
        "warranty": true
    },
    {
        "location": "台南店",
        "year": "2020",
        "brand": "三陽",
        "shopee_code": "1107843",
        "ruten_code": "0019000200020004",
        "model": "三陽 JETS 125 (ABS)",
        "tag": "#5991",
        "condition": "檢查和更換耗材，確保車輛運作順暢",
        "mileage": "519XX km",
        "images": [
            "https://cdn.store-assets.com/s/1336053/i/87377477.jpeg",
            "https://cdn.store-assets.com/s/1336053/i/87377480.jpeg",
            "https://cdn.store-assets.com/s/1336053/i/87377481.jpeg",
            "https://cdn.store-assets.com/s/1336053/i/87377479.jpeg",
            "https://cdn.store-assets.com/s/1336053/i/87377478.jpeg",
            "https://cdn.store-assets.com/s/1336053/i/87377475.jpeg",
            "https://cdn.store-assets.com/s/1336053/i/87377474.jpeg",
            "https://cdn.store-assets.com/s/1336053/i/87377476.jpeg",
            "https://cdn.store-assets.com/s/1336053/i/87377472.jpeg"
        ],
        "price": "53000",
        "warranty": true
    }
]