[
    {
        "location": "台中旗艦店",
        "year": "2014",
        "brand": "三陽",
        "shopee_code": "1107843",
        "ruten_code": "0019000200020004",
        "model": "MII 110",
        "tag": "#882",
        "condition": "檢查和更換耗材，確保車輛運作順暢",
        "mileage": "28,XXX km",
        "images": [
            "https://cdn.store-assets.com/s/1336053/i/83514104.jpeg",
            "https://cdn.store-assets.com/s/1336053/i/83514109.jpeg",
            "https://cdn.store-assets.com/s/1336053/i/83514111.jpeg",
            "https://cdn.store-assets.com/s/1336053/i/83514116.jpeg",
            "https://cdn.store-assets.com/s/1336053/i/83514121.jpeg"
        ],
        "price": "3500000",
        "warranty": false
    },
    {
        "location": "台中旗艦店",
        "year": "2014",
        "brand": "光陽",
        "shopee_code": "1095314",
        "ruten_code": "0019000200020001",
        "model": "G6 150",
        "tag": "#897",
        "condition": "檢查和更換耗材，確保車輛運作順暢",
        "mileage": "59,XXX km",
        "images": [
            "https://cdn.store-assets.com/s/1336053/i/83497741.jpeg",
            "https://cdn.store-assets.com/s/1336053/i/83497742.jpeg",
            "https://cdn.store-assets.com/s/1336053/i/83497743.jpeg",
            "https://cdn.store-assets.com/s/1336053/i/83497744.jpeg",
            "https://cdn.store-assets.com/s/1336053/i/83497745.jpeg"
        ],
        "price": "3500000",
        "warranty": true
    },
    {
        "location": "台中旗艦店",
        "year": "2017",
        "brand": "光陽",
        "shopee_code": "1095314",
        "ruten_code": "0019000200020001",
        "model": "雷霆 S150 雙碟",
        "tag": "#6169",
        "condition": "檢查和更換耗材，確保車輛運作順暢",
        "mileage": "47,XXX km",
        "images": [
            "https://cdn.store-assets.com/s/1336053/i/83497144.jpeg",
            "https://cdn.store-assets.com/s/1336053/i/83497145.jpeg",
            "https://cdn.store-assets.com/s/1336053/i/83497163.jpeg",
            "https://cdn.store-assets.com/s/1336053/i/83497164.jpeg",
            "https://cdn.store-assets.com/s/1336053/i/83497166.jpeg"
        ],
        "price": "4500000",
        "warranty": true
    },
    {
        "location": "台中旗艦店",
        "year": "2021",
        "brand": "哈特佛",
        "shopee_code": "1089745",
        "ruten_code": "9999999999999999",
        "model": "雲豹 223H",
        "tag": "#7012",
        "condition": "檢查和更換耗材，確保車輛運作順暢",
        "mileage": "15,XXX km",
        "images": [
            "https://cdn.store-assets.com/s/1336053/i/83490377.jpeg",
            "https://cdn.store-assets.com/s/1336053/i/83490386.jpeg",
            "https://cdn.store-assets.com/s/1336053/i/83490390.jpeg",
            "https://cdn.store-assets.com/s/1336053/i/83490392.jpeg",
            "https://cdn.store-assets.com/s/1336053/i/83490393.jpeg"
        ],
        "price": "5999900",
        "warranty": false
    },
    {
        "location": "台中旗艦店",
        "year": "2019",
        "brand": "光陽",
        "shopee_code": "1095314",
        "ruten_code": "0019000200020001",
        "model": "VJR 125",
        "tag": "#9328",
        "condition": "檢查和更換耗材，確保車輛運作順暢",
        "mileage": "24,XXX km",
        "images": [
            "https://cdn.store-assets.com/s/1336053/i/83490053.jpeg",
            "https://cdn.store-assets.com/s/1336053/i/83490055.jpeg",
            "https://cdn.store-assets.com/s/1336053/i/83490057.jpeg",
            "https://cdn.store-assets.com/s/1336053/i/83490060.jpeg",
            "https://cdn.store-assets.com/s/1336053/i/83490061.jpeg"
        ],
        "price": "4500000",
        "warranty": true
    },
    {
        "location": "台中旗艦店",
        "year": "2021",
        "brand": "光陽",
        "shopee_code": "1095314",
        "ruten_code": "0019000200020001",
        "model": "KRV 180",
        "tag": "#1552",
        "condition": "檢查和更換耗材，確保車輛運作順暢",
        "mileage": "14,XXX km",
        "images": [
            "https://cdn.store-assets.com/s/1336053/i/83399218.jpeg",
            "https://cdn.store-assets.com/s/1336053/i/83399219.jpeg",
            "https://cdn.store-assets.com/s/1336053/i/83399220.jpeg",
            "https://cdn.store-assets.com/s/1336053/i/83399222.jpeg",
            "https://cdn.store-assets.com/s/1336053/i/83399223.jpeg"
        ],
        "price": "7300000",
        "warranty": true
    },
    {
        "location": "台中旗艦店",
        "year": "2016",
        "brand": "山葉",
        "shopee_code": "1802940",
        "ruten_code": "0019000200020006",
        "model": "FORCE 155",
        "tag": "#5139",
        "condition": "檢查和更換耗材，確保車輛運作順暢",
        "mileage": "15,XXX km",
        "images": [
            "https://cdn.store-assets.com/s/1336053/i/83396017.jpeg",
            "https://cdn.store-assets.com/s/1336053/i/83396021.jpeg",
            "https://cdn.store-assets.com/s/1336053/i/83396024.jpeg",
            "https://cdn.store-assets.com/s/1336053/i/83396029.jpeg",
            "https://cdn.store-assets.com/s/1336053/i/83396035.jpeg"
        ],
        "price": "5300000",
        "warranty": true
    },
    {
        "location": "台中旗艦店",
        "year": "2020",
        "brand": "山葉",
        "shopee_code": "1802940",
        "ruten_code": "0019000200020006",
        "model": "勁戰五代 125 雙碟",
        "tag": "#6605",
        "condition": "檢查和更換耗材，確保車輛運作順暢",
        "mileage": "26,XXX km",
        "images": [
            "https://cdn.store-assets.com/s/1336053/i/83395793.jpeg",
            "https://cdn.store-assets.com/s/1336053/i/83395796.jpeg",
            "https://cdn.store-assets.com/s/1336053/i/83395800.jpeg",
            "https://cdn.store-assets.com/s/1336053/i/83395803.jpeg",
            "https://cdn.store-assets.com/s/1336053/i/83395811.jpeg"
        ],
        "price": "5800000",
        "warranty": true
    },
    {
        "location": "台中旗艦店",
        "year": "2023",
        "brand": "三陽",
        "shopee_code": "1107843",
        "ruten_code": "0019000200020004",
        "model": "MMBCU",
        "tag": "#2655",
        "condition": "檢查和更換耗材，確保車輛運作順暢",
        "mileage": "6,XXX km",
        "images": [
            "https://cdn.store-assets.com/s/1336053/i/83395423.jpeg",
            "https://cdn.store-assets.com/s/1336053/i/83395426.jpeg",
            "https://cdn.store-assets.com/s/1336053/i/83395438.jpeg",
            "https://cdn.store-assets.com/s/1336053/i/83395447.jpeg",
            "https://cdn.store-assets.com/s/1336053/i/83395453.jpeg"
        ],
        "price": "9800000",
        "warranty": true
    },
    {
        "location": "台中旗艦店",
        "year": "2014",
        "brand": "PGO",
        "shopee_code": "1101057",
        "ruten_code": "0019000200020002",
        "model": "JBUBU 115",
        "tag": "#8000",
        "condition": "檢查和更換耗材，確保車輛運作順暢",
        "mileage": "46,XXX km",
        "images": [
            "https://cdn.store-assets.com/s/1336053/i/83162059.jpeg",
            "https://cdn.store-assets.com/s/1336053/i/83162060.jpeg",
            "https://cdn.store-assets.com/s/1336053/i/83162061.jpeg",
            "https://cdn.store-assets.com/s/1336053/i/83162063.jpeg",
            "https://cdn.store-assets.com/s/1336053/i/83162064.jpeg"
        ],
        "price": "3500000",
        "warranty": true
    },
    {
        "location": "台中旗艦店",
        "year": "2021",
        "brand": "山葉",
        "shopee_code": "1802940",
        "ruten_code": "0019000200020006",
        "model": "FZS 150",
        "tag": "#1279",
        "condition": "檢查和更換耗材，確保車輛運作順暢",
        "mileage": "15,XXX km",
        "images": [
            "https://cdn.store-assets.com/s/1336053/i/83159650.jpeg",
            "https://cdn.store-assets.com/s/1336053/i/83159651.jpeg",
            "https://cdn.store-assets.com/s/1336053/i/83159652.jpeg",
            "https://cdn.store-assets.com/s/1336053/i/83159656.jpeg",
            "https://cdn.store-assets.com/s/1336053/i/83159657.jpeg"
        ],
        "price": "4999900",
        "warranty": false
    },
    {
        "location": "台中旗艦店",
        "year": "2020",
        "brand": "本田",
        "shopee_code": "1146583",
        "ruten_code": "0019000200020008",
        "model": "CB 300R",
        "tag": "#0869",
        "condition": "檢查和更換耗材，確保車輛運作順暢",
        "mileage": "16,XXX km",
        "images": [
            "https://cdn.store-assets.com/s/1336053/i/83133330.jpeg",
            "https://cdn.store-assets.com/s/1336053/i/83133333.jpeg",
            "https://cdn.store-assets.com/s/1336053/i/83133334.jpeg",
            "https://cdn.store-assets.com/s/1336053/i/83133354.jpeg",
            "https://cdn.store-assets.com/s/1336053/i/83133361.jpeg"
        ],
        "price": "9500000",
        "warranty": false
    },
    {
        "location": "台中旗艦店",
        "year": "2016",
        "brand": "三陽",
        "shopee_code": "1107843",
        "ruten_code": "0019000200020004",
        "model": "GT 125 鼓煞",
        "tag": "#1153",
        "condition": "檢查和更換耗材，確保車輛運作順暢",
        "mileage": "35,XXX km",
        "images": [
            "https://cdn.store-assets.com/s/1336053/i/83131360.jpeg",
            "https://cdn.store-assets.com/s/1336053/i/83131362.jpeg",
            "https://cdn.store-assets.com/s/1336053/i/83131363.jpeg",
            "https://cdn.store-assets.com/s/1336053/i/83131365.jpeg",
            "https://cdn.store-assets.com/s/1336053/i/83131372.jpeg"
        ],
        "price": "2999900",
        "warranty": true
    },
    {
        "location": "台中旗艦店",
        "year": "2021",
        "brand": "光陽",
        "shopee_code": "1095314",
        "ruten_code": "0019000200020001",
        "model": "KRV 180",
        "tag": "#5828",
        "condition": "檢查和更換耗材，確保車輛運作順暢",
        "mileage": "20,XXX km",
        "images": [
            "https://cdn.store-assets.com/s/1336053/i/83129827.jpeg",
            "https://cdn.store-assets.com/s/1336053/i/83129830.jpeg",
            "https://cdn.store-assets.com/s/1336053/i/83129842.jpeg",
            "https://cdn.store-assets.com/s/1336053/i/83129845.jpeg",
            "https://cdn.store-assets.com/s/1336053/i/83129850.jpeg"
        ],
        "price": "7000000",
        "warranty": true
    },
    {
        "location": "台中旗艦店",
        "year": "2013",
        "brand": "山葉",
        "shopee_code": "1802940",
        "ruten_code": "0019000200020006",
        "model": "BWSX 125",
        "tag": "#208",
        "condition": "檢查和更換耗材，確保車輛運作順暢",
        "mileage": "6 km",
        "images": [
            "https://cdn.store-assets.com/s/1336053/i/83107775.jpeg",
            "https://cdn.store-assets.com/s/1336053/i/83107778.jpeg",
            "https://cdn.store-assets.com/s/1336053/i/83107785.jpeg",
            "https://cdn.store-assets.com/s/1336053/i/83107788.jpeg",
            "https://cdn.store-assets.com/s/1336053/i/83107789.jpeg"
        ],
        "price": "2999900",
        "warranty": true
    },
    {
        "location": "台中旗艦店",
        "year": "2012",
        "brand": "三陽",
        "shopee_code": "1107843",
        "ruten_code": "0019000200020004",
        "model": "MII 110 鼓煞",
        "tag": "#908",
        "condition": "檢查和更換耗材，確保車輛運作順暢",
        "mileage": "34,XXX km",
        "images": [
            "https://cdn.store-assets.com/s/1336053/i/83045706.jpeg",
            "https://cdn.store-assets.com/s/1336053/i/83045707.jpeg",
            "https://cdn.store-assets.com/s/1336053/i/83045708.jpeg",
            "https://cdn.store-assets.com/s/1336053/i/83045711.jpeg",
            "https://cdn.store-assets.com/s/1336053/i/83045713.jpeg"
        ],
        "price": "3300000",
        "warranty": true
    },
    {
        "location": "台中旗艦店",
        "year": "2022",
        "brand": "BRIXTON",
        "shopee_code": "999999",
        "ruten_code": "9999999999999999",
        "model": "BX150",
        "tag": "#9936",
        "condition": "檢查和更換耗材，確保車輛運作順暢",
        "mileage": "6,XXX km",
        "images": [
            "https://cdn.store-assets.com/s/1336053/i/83028383.jpeg",
            "https://cdn.store-assets.com/s/1336053/i/83028384.jpeg",
            "https://cdn.store-assets.com/s/1336053/i/83028385.jpeg",
            "https://cdn.store-assets.com/s/1336053/i/83028386.jpeg",
            "https://cdn.store-assets.com/s/1336053/i/83028387.jpeg"
        ],
        "price": "7999900",
        "warranty": false
    },
    {
        "location": "台中旗艦店",
        "year": "2020",
        "brand": "三陽",
        "shopee_code": "1107843",
        "ruten_code": "0019000200020004",
        "model": "JET SR 125",
        "tag": "#9558",
        "condition": "檢查和更換耗材，確保車輛運作順暢",
        "mileage": "36,XXX km",
        "images": [
            "https://cdn.store-assets.com/s/1336053/i/82909290.jpeg",
            "https://cdn.store-assets.com/s/1336053/i/82909291.jpeg",
            "https://cdn.store-assets.com/s/1336053/i/82909292.jpeg",
            "https://cdn.store-assets.com/s/1336053/i/82909293.jpeg",
            "https://cdn.store-assets.com/s/1336053/i/82909294.jpeg"
        ],
        "price": "6800000",
        "warranty": true
    },
    {
        "location": "台中旗艦店",
        "year": "2020",
        "brand": "睿能",
        "shopee_code": "1091869",
        "ruten_code": "9999999999999999",
        "model": "GOGORO 2 DELIGHT",
        "tag": "#9652",
        "condition": "檢查和更換耗材，確保車輛運作順暢",
        "mileage": "9,XXX km",
        "images": [
            "https://cdn.store-assets.com/s/1336053/i/82907853.jpeg",
            "https://cdn.store-assets.com/s/1336053/i/82907858.jpeg",
            "https://cdn.store-assets.com/s/1336053/i/82907860.jpeg",
            "https://cdn.store-assets.com/s/1336053/i/82907863.jpeg",
            "https://cdn.store-assets.com/s/1336053/i/82907866.jpeg"
        ],
        "price": "3500000",
        "warranty": false
    },
    {
        "location": "台中旗艦店",
        "year": "2018",
        "brand": "睿能",
        "shopee_code": "1091869",
        "ruten_code": "9999999999999999",
        "model": "GOGORO 2 DELIGHT",
        "tag": "#5190",
        "condition": "檢查和更換耗材，確保車輛運作順暢",
        "mileage": "15,XXX km",
        "images": [
            "https://cdn.store-assets.com/s/1336053/i/83846428.jpeg",
            "https://cdn.store-assets.com/s/1336053/i/83846430.jpeg",
            "https://cdn.store-assets.com/s/1336053/i/83846434.jpeg",
            "https://cdn.store-assets.com/s/1336053/i/83846437.jpeg",
            "https://cdn.store-assets.com/s/1336053/i/83846441.jpeg"
        ],
        "price": "2999900",
        "warranty": false
    },
    {
        "location": "台中旗艦店",
        "year": "2021",
        "brand": "光陽",
        "shopee_code": "1095314",
        "ruten_code": "0019000200020001",
        "model": "KRV 180",
        "tag": "#9892",
        "condition": "檢查和更換耗材，確保車輛運作順暢",
        "mileage": "23,XXX km",
        "images": [
            "https://cdn.store-assets.com/s/1336053/i/82907587.jpeg",
            "https://cdn.store-assets.com/s/1336053/i/82907596.jpeg",
            "https://cdn.store-assets.com/s/1336053/i/82907597.jpeg",
            "https://cdn.store-assets.com/s/1336053/i/82907598.jpeg",
            "https://cdn.store-assets.com/s/1336053/i/82907600.jpeg"
        ],
        "price": "7200000",
        "warranty": true
    },
    {
        "location": "台中旗艦店",
        "year": "2009",
        "brand": "山葉",
        "shopee_code": "1802940",
        "ruten_code": "0019000200020006",
        "model": "CUXI 100 噴射",
        "tag": "#529",
        "condition": "檢查和更換耗材，確保車輛運作順暢",
        "mileage": "30,XXX km",
        "images": [
            "https://cdn.store-assets.com/s/1336053/i/82778362.jpeg",
            "https://cdn.store-assets.com/s/1336053/i/82778373.jpeg",
            "https://cdn.store-assets.com/s/1336053/i/82778392.jpeg",
            "https://cdn.store-assets.com/s/1336053/i/82778395.jpeg",
            "https://cdn.store-assets.com/s/1336053/i/82778402.jpeg"
        ],
        "price": "2500000",
        "warranty": false
    },
    {
        "location": "台中旗艦店",
        "year": "2017",
        "brand": "光陽",
        "shopee_code": "1095314",
        "ruten_code": "0019000200020001",
        "model": "GP 125 噴射",
        "tag": "#6633",
        "condition": "檢查和更換耗材，確保車輛運作順暢",
        "mileage": "43,XXX km",
        "images": [
            "https://cdn.store-assets.com/s/1336053/i/82725506.jpeg",
            "https://cdn.store-assets.com/s/1336053/i/82725507.jpeg",
            "https://cdn.store-assets.com/s/1336053/i/82725508.jpeg",
            "https://cdn.store-assets.com/s/1336053/i/82725509.jpeg",
            "https://cdn.store-assets.com/s/1336053/i/82725510.jpeg"
        ],
        "price": "3500000",
        "warranty": true
    },
    {
        "location": "台中旗艦店",
        "year": "2021",
        "brand": "三陽",
        "shopee_code": "1107843",
        "ruten_code": "0019000200020004",
        "model": "FIDDLE 125",
        "tag": "#0351",
        "condition": "檢查和更換耗材，確保車輛運作順暢",
        "mileage": "19,XXX km",
        "images": [
            "https://cdn.store-assets.com/s/1336053/i/82725090.jpeg",
            "https://cdn.store-assets.com/s/1336053/i/82725092.jpeg",
            "https://cdn.store-assets.com/s/1336053/i/82725093.jpeg",
            "https://cdn.store-assets.com/s/1336053/i/82725094.jpeg",
            "https://cdn.store-assets.com/s/1336053/i/82725095.jpeg"
        ],
        "price": "5300000",
        "warranty": true
    },
    {
        "location": "台中旗艦店",
        "year": "2020",
        "brand": "睿能",
        "shopee_code": "1091869",
        "ruten_code": "9999999999999999",
        "model": "GOGORO 2 DELIGHT",
        "tag": "#9787",
        "condition": "檢查和更換耗材，確保車輛運作順暢",
        "mileage": "5,XXX km",
        "images": [
            "https://cdn.store-assets.com/s/1336053/i/82723040.jpeg",
            "https://cdn.store-assets.com/s/1336053/i/82723041.jpeg",
            "https://cdn.store-assets.com/s/1336053/i/82723042.jpeg",
            "https://cdn.store-assets.com/s/1336053/i/82723043.jpeg",
            "https://cdn.store-assets.com/s/1336053/i/82723044.jpeg"
        ],
        "price": "3300000",
        "warranty": false
    },
    {
        "location": "台中旗艦店",
        "year": "2015",
        "brand": "三陽",
        "shopee_code": "1107843",
        "ruten_code": "0019000200020004",
        "model": "GTS 300 IE",
        "tag": "#690",
        "condition": "檢查和更換耗材，確保車輛運作順暢",
        "mileage": "58,XXX km",
        "images": [
            "https://cdn.store-assets.com/s/1336053/i/82602217.jpeg",
            "https://cdn.store-assets.com/s/1336053/i/82602218.jpeg",
            "https://cdn.store-assets.com/s/1336053/i/82602219.jpeg",
            "https://cdn.store-assets.com/s/1336053/i/82602220.jpeg",
            "https://cdn.store-assets.com/s/1336053/i/82602221.jpeg"
        ],
        "price": "4300000",
        "warranty": false
    },
    {
        "location": "台中旗艦店",
        "year": "2021",
        "brand": "三陽",
        "shopee_code": "1107843",
        "ruten_code": "0019000200020004",
        "model": "DRG 158 ABS 六期",
        "tag": "#6811",
        "condition": "檢查和更換耗材，確保車輛運作順暢",
        "mileage": "32,XXX km",
        "images": [
            "https://cdn.store-assets.com/s/1336053/i/82805652.jpeg",
            "https://cdn.store-assets.com/s/1336053/i/82805653.jpeg",
            "https://cdn.store-assets.com/s/1336053/i/82805655.jpeg",
            "https://cdn.store-assets.com/s/1336053/i/82805660.jpeg",
            "https://cdn.store-assets.com/s/1336053/i/82805665.jpeg"
        ],
        "price": "7200000",
        "warranty": true
    },
    {
        "location": "台中旗艦店",
        "year": "2019",
        "brand": "睿能",
        "shopee_code": "1091869",
        "ruten_code": "9999999999999999",
        "model": "GOGORO S2",
        "tag": "#1197",
        "condition": "檢查和更換耗材，確保車輛運作順暢",
        "mileage": "13,XXX km",
        "images": [
            "https://cdn.store-assets.com/s/1336053/i/82599760.jpeg",
            "https://cdn.store-assets.com/s/1336053/i/82599766.jpeg",
            "https://cdn.store-assets.com/s/1336053/i/82599770.jpeg",
            "https://cdn.store-assets.com/s/1336053/i/82599771.jpeg",
            "https://cdn.store-assets.com/s/1336053/i/82599779.jpeg"
        ],
        "price": "3800000",
        "warranty": false
    },
    {
        "location": "台中旗艦店",
        "year": "2021",
        "brand": "宏佳騰",
        "shopee_code": "1082956",
        "ruten_code": "0019000200020009",
        "model": "MY 150 RETRO",
        "tag": "#7130",
        "condition": "檢查和更換耗材，確保車輛運作順暢",
        "mileage": "17,XXX km",
        "images": [
            "https://cdn.store-assets.com/s/1336053/i/82586212.jpeg",
            "https://cdn.store-assets.com/s/1336053/i/82586213.jpeg",
            "https://cdn.store-assets.com/s/1336053/i/82586214.jpeg",
            "https://cdn.store-assets.com/s/1336053/i/82586215.jpeg",
            "https://cdn.store-assets.com/s/1336053/i/82586216.jpeg"
        ],
        "price": "5300000",
        "warranty": false
    },
    {
        "location": "台中旗艦店",
        "year": "2021",
        "brand": "山葉",
        "shopee_code": "1802940",
        "ruten_code": "0019000200020006",
        "model": "R15 V3 倒叉",
        "tag": "#7272",
        "condition": "檢查和更換耗材，確保車輛運作順暢",
        "mileage": "21,XXX km",
        "images": [
            "https://cdn.store-assets.com/s/1336053/i/82586154.jpeg",
            "https://cdn.store-assets.com/s/1336053/i/82586155.jpeg",
            "https://cdn.store-assets.com/s/1336053/i/82586156.jpeg",
            "https://cdn.store-assets.com/s/1336053/i/82586157.jpeg",
            "https://cdn.store-assets.com/s/1336053/i/82586158.jpeg"
        ],
        "price": "7200000",
        "warranty": false
    },
    {
        "location": "台中旗艦店",
        "year": "2022",
        "brand": "三陽",
        "shopee_code": "1107843",
        "ruten_code": "0019000200020004",
        "model": "JET SL 125",
        "tag": "#7392",
        "condition": "檢查和更換耗材，確保車輛運作順暢",
        "mileage": "22,XXX km",
        "images": [
            "https://cdn.store-assets.com/s/1336053/i/82586079.jpeg",
            "https://cdn.store-assets.com/s/1336053/i/82586080.jpeg",
            "https://cdn.store-assets.com/s/1336053/i/82586082.jpeg",
            "https://cdn.store-assets.com/s/1336053/i/82586083.jpeg",
            "https://cdn.store-assets.com/s/1336053/i/82586084.jpeg"
        ],
        "price": "8300000",
        "warranty": true
    },
    {
        "location": "台中旗艦店",
        "year": "2023",
        "brand": "光陽",
        "shopee_code": "1095314",
        "ruten_code": "0019000200020001",
        "model": "GP 125 噴射",
        "tag": "#6303",
        "condition": "檢查和更換耗材，確保車輛運作順暢",
        "mileage": "2,XXX km",
        "images": [
            "https://cdn.store-assets.com/s/1336053/i/82541972.jpeg",
            "https://cdn.store-assets.com/s/1336053/i/82541973.jpeg",
            "https://cdn.store-assets.com/s/1336053/i/82541980.jpeg",
            "https://cdn.store-assets.com/s/1336053/i/82541981.jpeg",
            "https://cdn.store-assets.com/s/1336053/i/82541982.jpeg"
        ],
        "price": "4200000",
        "warranty": true
    },
    {
        "location": "台中旗艦店",
        "year": "2018",
        "brand": "宏佳騰",
        "shopee_code": "1082956",
        "ruten_code": "0019000200020009",
        "model": "ELITE 300R",
        "tag": "#0872",
        "condition": "檢查和更換耗材，確保車輛運作順暢",
        "mileage": "52,XXX km",
        "images": [
            "https://cdn.store-assets.com/s/1336053/i/82541461.jpeg",
            "https://cdn.store-assets.com/s/1336053/i/82541462.jpeg",
            "https://cdn.store-assets.com/s/1336053/i/82541463.jpeg",
            "https://cdn.store-assets.com/s/1336053/i/82541464.jpeg",
            "https://cdn.store-assets.com/s/1336053/i/82541467.jpeg"
        ],
        "price": "4999900",
        "warranty": false
    },
    {
        "location": "台中旗艦店",
        "year": "2023",
        "brand": "三陽",
        "shopee_code": "1107843",
        "ruten_code": "0019000200020004",
        "model": "JET SL 125",
        "tag": "#3026",
        "condition": "檢查和更換耗材，確保車輛運作順暢",
        "mileage": "7,XXX km",
        "images": [
            "https://cdn.store-assets.com/s/1336053/i/82536663.jpeg",
            "https://cdn.store-assets.com/s/1336053/i/82536664.jpeg",
            "https://cdn.store-assets.com/s/1336053/i/82536665.jpeg",
            "https://cdn.store-assets.com/s/1336053/i/82536666.jpeg",
            "https://cdn.store-assets.com/s/1336053/i/82536667.jpeg"
        ],
        "price": "8500000",
        "warranty": true
    },
    {
        "location": "台中旗艦店",
        "year": "2014",
        "brand": "光陽",
        "shopee_code": "1095314",
        "ruten_code": "0019000200020001",
        "model": "G6E 125",
        "tag": "#8227",
        "condition": "檢查和更換耗材，確保車輛運作順暢",
        "mileage": "39,XXX km",
        "images": [
            "https://cdn.store-assets.com/s/1336053/i/82536573.jpeg",
            "https://cdn.store-assets.com/s/1336053/i/82536574.jpeg",
            "https://cdn.store-assets.com/s/1336053/i/82536575.jpeg",
            "https://cdn.store-assets.com/s/1336053/i/82536579.jpeg",
            "https://cdn.store-assets.com/s/1336053/i/82536580.jpeg"
        ],
        "price": "3500000",
        "warranty": true
    },
    {
        "location": "台中旗艦店",
        "year": "2022",
        "brand": "山葉",
        "shopee_code": "1802940",
        "ruten_code": "0019000200020006",
        "model": "勁戰六代",
        "tag": "#3609",
        "condition": "檢查和更換耗材，確保車輛運作順暢",
        "mileage": "47,XXX km",
        "images": [
            "https://cdn.store-assets.com/s/1336053/i/82472787.jpeg",
            "https://cdn.store-assets.com/s/1336053/i/82472788.jpeg",
            "https://cdn.store-assets.com/s/1336053/i/82472790.jpeg",
            "https://cdn.store-assets.com/s/1336053/i/82472791.jpeg",
            "https://cdn.store-assets.com/s/1336053/i/82472792.jpeg"
        ],
        "price": "7200000",
        "warranty": true
    },
    {
        "location": "台中旗艦店",
        "year": "2019",
        "brand": "三陽",
        "shopee_code": "1107843",
        "ruten_code": "0019000200020004",
        "model": "野狼 300",
        "tag": "#1907",
        "condition": "檢查和更換耗材，確保車輛運作順暢",
        "mileage": "20,XXX km",
        "images": [
            "https://cdn.store-assets.com/s/1336053/i/82472533.jpeg",
            "https://cdn.store-assets.com/s/1336053/i/82472534.jpeg",
            "https://cdn.store-assets.com/s/1336053/i/82472535.jpeg",
            "https://cdn.store-assets.com/s/1336053/i/82472536.jpeg",
            "https://cdn.store-assets.com/s/1336053/i/82472537.jpeg"
        ],
        "price": "7800000",
        "warranty": false
    },
    {
        "location": "台中旗艦店",
        "year": "2019",
        "brand": "睿能",
        "shopee_code": "1091869",
        "ruten_code": "9999999999999999",
        "model": "GOGORO 2 DELIGHT",
        "tag": "#9981",
        "condition": "檢查和更換耗材，確保車輛運作順暢",
        "mileage": "16,XXX km",
        "images": [
            "https://cdn.store-assets.com/s/1336053/i/82470957.jpeg",
            "https://cdn.store-assets.com/s/1336053/i/82470958.jpeg",
            "https://cdn.store-assets.com/s/1336053/i/82470959.jpeg",
            "https://cdn.store-assets.com/s/1336053/i/82470960.jpeg",
            "https://cdn.store-assets.com/s/1336053/i/82470961.jpeg"
        ],
        "price": "2999900",
        "warranty": false
    },
    {
        "location": "台中旗艦店",
        "year": "2011",
        "brand": "光陽",
        "shopee_code": "1095314",
        "ruten_code": "0019000200020001",
        "model": "雷霆 150 RACING",
        "tag": "#238",
        "condition": "檢查和更換耗材，確保車輛運作順暢",
        "mileage": "49,XXX km",
        "images": [
            "https://cdn.store-assets.com/s/1336053/i/82362843.jpeg",
            "https://cdn.store-assets.com/s/1336053/i/82362844.jpeg",
            "https://cdn.store-assets.com/s/1336053/i/82362846.jpeg",
            "https://cdn.store-assets.com/s/1336053/i/82362847.jpeg",
            "https://cdn.store-assets.com/s/1336053/i/82362848.jpeg"
        ],
        "price": "2999900",
        "warranty": false
    },
    {
        "location": "台中旗艦店",
        "year": "2022",
        "brand": "三陽",
        "shopee_code": "1107843",
        "ruten_code": "0019000200020004",
        "model": "DRG 158 TCS 七期",
        "tag": "#5205",
        "condition": "檢查和更換耗材，確保車輛運作順暢",
        "mileage": "34,XXX km",
        "images": [
            "https://cdn.store-assets.com/s/1336053/i/82280317.jpeg",
            "https://cdn.store-assets.com/s/1336053/i/82280318.jpeg",
            "https://cdn.store-assets.com/s/1336053/i/82280319.jpeg",
            "https://cdn.store-assets.com/s/1336053/i/82280320.jpeg",
            "https://cdn.store-assets.com/s/1336053/i/82280322.jpeg"
        ],
        "price": "7500000",
        "warranty": true
    },
    {
        "location": "台中旗艦店",
        "year": "2019",
        "brand": "光陽",
        "shopee_code": "1095314",
        "ruten_code": "0019000200020001",
        "model": "NICE 100",
        "tag": "#6751",
        "condition": "檢查和更換耗材，確保車輛運作順暢",
        "mileage": "5,XXX km",
        "images": [
            "https://cdn.store-assets.com/s/1336053/i/82278894.jpeg",
            "https://cdn.store-assets.com/s/1336053/i/82278895.jpeg",
            "https://cdn.store-assets.com/s/1336053/i/82278896.jpeg",
            "https://cdn.store-assets.com/s/1336053/i/82278898.jpeg",
            "https://cdn.store-assets.com/s/1336053/i/82278899.jpeg"
        ],
        "price": "3500000",
        "warranty": true
    },
    {
        "location": "台中旗艦店",
        "year": "2014",
        "brand": "光陽",
        "shopee_code": "1095314",
        "ruten_code": "0019000200020001",
        "model": "MANY 125",
        "tag": "#788",
        "condition": "檢查和更換耗材，確保車輛運作順暢",
        "mileage": "75,XXX km",
        "images": [
            "https://cdn.store-assets.com/s/1336053/i/82278765.jpeg",
            "https://cdn.store-assets.com/s/1336053/i/82278767.jpeg",
            "https://cdn.store-assets.com/s/1336053/i/82278769.jpeg",
            "https://cdn.store-assets.com/s/1336053/i/82278770.jpeg",
            "https://cdn.store-assets.com/s/1336053/i/82278774.jpeg"
        ],
        "price": "3500000",
        "warranty": true
    },
    {
        "location": "台中旗艦店",
        "year": "2015",
        "brand": "山葉",
        "shopee_code": "1802940",
        "ruten_code": "0019000200020006",
        "model": "SMAX 155",
        "tag": "#7977",
        "condition": "檢查和更換耗材，確保車輛運作順暢",
        "mileage": "33,XXX km",
        "images": [
            "https://cdn.store-assets.com/s/1336053/i/82276123.jpeg",
            "https://cdn.store-assets.com/s/1336053/i/82276124.jpeg",
            "https://cdn.store-assets.com/s/1336053/i/82276125.jpeg",
            "https://cdn.store-assets.com/s/1336053/i/82276126.jpeg",
            "https://cdn.store-assets.com/s/1336053/i/82276127.jpeg"
        ],
        "price": "4500000",
        "warranty": true
    },
    {
        "location": "台中旗艦店",
        "year": "2019",
        "brand": "睿能",
        "shopee_code": "1091869",
        "ruten_code": "9999999999999999",
        "model": "GOGORO 2 DELIGHT",
        "tag": "#0368",
        "condition": "檢查和更換耗材，確保車輛運作順暢",
        "mileage": "14,XXX km",
        "images": [
            "https://cdn.store-assets.com/s/1336053/i/82142051.jpeg",
            "https://cdn.store-assets.com/s/1336053/i/82142053.jpeg",
            "https://cdn.store-assets.com/s/1336053/i/82142057.jpeg",
            "https://cdn.store-assets.com/s/1336053/i/82142058.jpeg",
            "https://cdn.store-assets.com/s/1336053/i/82142059.jpeg"
        ],
        "price": "2999900",
        "warranty": false
    },
    {
        "location": "台中旗艦店",
        "year": "2010",
        "brand": "三陽",
        "shopee_code": "1107843",
        "ruten_code": "0019000200020004",
        "model": "T1 150",
        "tag": "#168",
        "condition": "檢查和更換耗材，確保車輛運作順暢",
        "mileage": "9,XXX km",
        "images": [
            "https://cdn.store-assets.com/s/1336053/i/82141963.jpeg",
            "https://cdn.store-assets.com/s/1336053/i/82141964.jpeg",
            "https://cdn.store-assets.com/s/1336053/i/82141966.jpeg",
            "https://cdn.store-assets.com/s/1336053/i/82141967.jpeg",
            "https://cdn.store-assets.com/s/1336053/i/82141968.jpeg"
        ],
        "price": "2800000",
        "warranty": false
    },
    {
        "location": "台中旗艦店",
        "year": "2018",
        "brand": "睿能",
        "shopee_code": "1091869",
        "ruten_code": "9999999999999999",
        "model": "GOGORO 2 DELUXE",
        "tag": "#2950",
        "condition": "檢查和更換耗材，確保車輛運作順暢",
        "mileage": "15,XXX km",
        "images": [
            "https://cdn.store-assets.com/s/1336053/i/82115493.jpeg",
            "https://cdn.store-assets.com/s/1336053/i/82115494.jpeg",
            "https://cdn.store-assets.com/s/1336053/i/82115495.jpeg",
            "https://cdn.store-assets.com/s/1336053/i/82115496.jpeg",
            "https://cdn.store-assets.com/s/1336053/i/82115497.jpeg"
        ],
        "price": "3200000",
        "warranty": false
    },
    {
        "location": "台中旗艦店",
        "year": "2019",
        "brand": "山葉",
        "shopee_code": "1802940",
        "ruten_code": "0019000200020006",
        "model": "勁戰五代 125 雙碟",
        "tag": "#0935",
        "condition": "檢查和更換耗材，確保車輛運作順暢",
        "mileage": "31,XXX km",
        "images": [
            "https://cdn.store-assets.com/s/1336053/i/82034783.jpeg",
            "https://cdn.store-assets.com/s/1336053/i/82034785.jpeg",
            "https://cdn.store-assets.com/s/1336053/i/82034786.jpeg",
            "https://cdn.store-assets.com/s/1336053/i/82034789.jpeg",
            "https://cdn.store-assets.com/s/1336053/i/82034797.jpeg"
        ],
        "price": "5800000",
        "warranty": true
    },
    {
        "location": "台中旗艦店",
        "year": "2020",
        "brand": "哈特佛",
        "shopee_code": "1089745",
        "ruten_code": "9999999999999999",
        "model": "雲豹 223",
        "tag": "#8618",
        "condition": "檢查和更換耗材，確保車輛運作順暢",
        "mileage": "3,XXX km",
        "images": [
            "https://cdn.store-assets.com/s/1336053/i/82033977.jpeg",
            "https://cdn.store-assets.com/s/1336053/i/82033984.jpeg",
            "https://cdn.store-assets.com/s/1336053/i/82033992.jpeg",
            "https://cdn.store-assets.com/s/1336053/i/82034024.jpeg",
            "https://cdn.store-assets.com/s/1336053/i/82034030.jpeg"
        ],
        "price": "5500000",
        "warranty": false
    },
    {
        "location": "台中旗艦店",
        "year": "2013",
        "brand": "山葉",
        "shopee_code": "1802940",
        "ruten_code": "0019000200020006",
        "model": "SMAX 155",
        "tag": "#788",
        "condition": "檢查和更換耗材，確保車輛運作順暢",
        "mileage": "43,XXX km",
        "images": [
            "https://cdn.store-assets.com/s/1336053/i/81953334.jpeg",
            "https://cdn.store-assets.com/s/1336053/i/81953335.jpeg",
            "https://cdn.store-assets.com/s/1336053/i/81953336.jpeg",
            "https://cdn.store-assets.com/s/1336053/i/81953337.jpeg",
            "https://cdn.store-assets.com/s/1336053/i/81953338.jpeg"
        ],
        "price": "4300000",
        "warranty": true
    },
    {
        "location": "台中旗艦店",
        "year": "2014",
        "brand": "山葉",
        "shopee_code": "1802940",
        "ruten_code": "0019000200020006",
        "model": "勁戰三代 125",
        "tag": "#778",
        "condition": "檢查和更換耗材，確保車輛運作順暢",
        "mileage": "27,XXX km",
        "images": [
            "https://cdn.store-assets.com/s/1336053/i/81649614.jpeg",
            "https://cdn.store-assets.com/s/1336053/i/81649615.jpeg",
            "https://cdn.store-assets.com/s/1336053/i/81649616.jpeg",
            "https://cdn.store-assets.com/s/1336053/i/81649624.jpeg",
            "https://cdn.store-assets.com/s/1336053/i/81649631.jpeg"
        ],
        "price": "3800000",
        "warranty": true
    },
    {
        "location": "台中旗艦店",
        "year": "2016",
        "brand": "宏佳騰",
        "shopee_code": "1082956",
        "ruten_code": "0019000200020009",
        "model": "MY 150",
        "tag": "#2525",
        "condition": "檢查和更換耗材，確保車輛運作順暢",
        "mileage": "8,XXX km",
        "images": [
            "https://cdn.store-assets.com/s/1336053/i/81644436.jpeg",
            "https://cdn.store-assets.com/s/1336053/i/81644445.jpeg",
            "https://cdn.store-assets.com/s/1336053/i/81644447.jpeg",
            "https://cdn.store-assets.com/s/1336053/i/81644452.jpeg",
            "https://cdn.store-assets.com/s/1336053/i/81644455.jpeg"
        ],
        "price": "3500000",
        "warranty": false
    },
    {
        "location": "台中旗艦店",
        "year": "2021",
        "brand": "光陽",
        "shopee_code": "1095314",
        "ruten_code": "0019000200020001",
        "model": "KRV 180",
        "tag": "#5515",
        "condition": "檢查和更換耗材，確保車輛運作順暢",
        "mileage": "38,XXX km",
        "images": [
            "https://cdn.store-assets.com/s/1336053/i/81417921.jpeg",
            "https://cdn.store-assets.com/s/1336053/i/81417922.jpeg",
            "https://cdn.store-assets.com/s/1336053/i/81417933.jpeg",
            "https://cdn.store-assets.com/s/1336053/i/81417935.jpeg",
            "https://cdn.store-assets.com/s/1336053/i/81417941.jpeg"
        ],
        "price": "7200000",
        "warranty": true
    },
    {
        "location": "台中旗艦店",
        "year": "2014",
        "brand": "光陽",
        "shopee_code": "1095314",
        "ruten_code": "0019000200020001",
        "model": "V2 125",
        "tag": "#930",
        "condition": "檢查和更換耗材，確保車輛運作順暢",
        "mileage": "28,XXX km",
        "images": [
            "https://cdn.store-assets.com/s/1336053/i/81114072.jpeg",
            "https://cdn.store-assets.com/s/1336053/i/81114077.jpeg",
            "https://cdn.store-assets.com/s/1336053/i/81114095.jpeg",
            "https://cdn.store-assets.com/s/1336053/i/81114101.jpeg",
            "https://cdn.store-assets.com/s/1336053/i/81114103.jpeg"
        ],
        "price": "2999900",
        "warranty": false
    },
    {
        "location": "台中旗艦店",
        "year": "2019",
        "brand": "睿能",
        "shopee_code": "1091869",
        "ruten_code": "9999999999999999",
        "model": "GOGORO 3 鑰匙版",
        "tag": "#6563",
        "condition": "檢查和更換耗材，確保車輛運作順暢",
        "mileage": "16,XXX km",
        "images": [
            "https://cdn.store-assets.com/s/1336053/i/80773166.jpeg",
            "https://cdn.store-assets.com/s/1336053/i/80773167.jpeg",
            "https://cdn.store-assets.com/s/1336053/i/80773176.jpeg",
            "https://cdn.store-assets.com/s/1336053/i/80773177.jpeg",
            "https://cdn.store-assets.com/s/1336053/i/80773178.jpeg"
        ],
        "price": "2700000",
        "warranty": false
    },
    {
        "location": "台中旗艦店",
        "year": "2019",
        "brand": "睿能",
        "shopee_code": "1091869",
        "ruten_code": "9999999999999999",
        "model": "GOGORO 3 鑰匙版",
        "tag": "#7510",
        "condition": "檢查和更換耗材，確保車輛運作順暢",
        "mileage": "11,XXX km",
        "images": [
            "https://cdn.store-assets.com/s/1336053/i/80673586.jpeg",
            "https://cdn.store-assets.com/s/1336053/i/80673589.jpeg",
            "https://cdn.store-assets.com/s/1336053/i/80673588.jpeg",
            "https://cdn.store-assets.com/s/1336053/i/80673587.jpeg",
            "https://cdn.store-assets.com/s/1336053/i/80673590.jpeg"
        ],
        "price": "2700000",
        "warranty": false
    },
    {
        "location": "台中旗艦店",
        "year": "2019",
        "brand": "睿能",
        "shopee_code": "1091869",
        "ruten_code": "9999999999999999",
        "model": "GOGORO 2 PLUS",
        "tag": "#8836",
        "condition": "檢查和更換耗材，確保車輛運作順暢",
        "mileage": "33,XXX km",
        "images": [
            "https://cdn.store-assets.com/s/1336053/i/80528599.jpeg",
            "https://cdn.store-assets.com/s/1336053/i/80528606.jpeg",
            "https://cdn.store-assets.com/s/1336053/i/80528630.jpeg",
            "https://cdn.store-assets.com/s/1336053/i/80528631.jpeg",
            "https://cdn.store-assets.com/s/1336053/i/80528632.jpeg"
        ],
        "price": "2400000",
        "warranty": false
    },
    {
        "location": "台中旗艦店",
        "year": "2015",
        "brand": "宏佳騰",
        "shopee_code": "1082956",
        "ruten_code": "0019000200020009",
        "model": "MY150",
        "tag": "#3391",
        "condition": "檢查和更換耗材，確保車輛運作順暢",
        "mileage": "30,XXX km",
        "images": [
            "https://cdn.store-assets.com/s/1336053/i/80476491.jpeg",
            "https://cdn.store-assets.com/s/1336053/i/80476492.jpeg",
            "https://cdn.store-assets.com/s/1336053/i/80476493.jpeg",
            "https://cdn.store-assets.com/s/1336053/i/80476494.jpeg",
            "https://cdn.store-assets.com/s/1336053/i/80476495.jpeg"
        ],
        "price": "3300000",
        "warranty": false
    },
    {
        "location": "台中旗艦店",
        "year": "2014",
        "brand": "光陽",
        "shopee_code": "1095314",
        "ruten_code": "0019000200020001",
        "model": "GP125",
        "tag": "#3692",
        "condition": "檢查和更換耗材，確保車輛運作順暢",
        "mileage": "30,XXX km",
        "images": [
            "https://cdn.store-assets.com/s/1336053/i/79725912.jpeg",
            "https://cdn.store-assets.com/s/1336053/i/79725913.jpeg",
            "https://cdn.store-assets.com/s/1336053/i/79725914.jpeg",
            "https://cdn.store-assets.com/s/1336053/i/79725915.jpeg",
            "https://cdn.store-assets.com/s/1336053/i/79725916.jpeg"
        ],
        "price": "2999900",
        "warranty": true
    },
    {
        "location": "台中旗艦店",
        "year": "2014",
        "brand": "光陽",
        "shopee_code": "1095314",
        "ruten_code": "0019000200020001",
        "model": "GP125",
        "tag": "#835",
        "condition": "檢查和更換耗材，確保車輛運作順暢",
        "mileage": "15,XXX km",
        "images": [
            "https://cdn.store-assets.com/s/1336053/i/79247719.jpeg",
            "https://cdn.store-assets.com/s/1336053/i/79247720.jpeg",
            "https://cdn.store-assets.com/s/1336053/i/79247717.jpeg",
            "https://cdn.store-assets.com/s/1336053/i/79247718.jpeg",
            "https://cdn.store-assets.com/s/1336053/i/79247716.jpeg"
        ],
        "price": "3200000",
        "warranty": true
    },
    {
        "location": "台中旗艦店",
        "year": "2019",
        "brand": "光陽",
        "shopee_code": "1095314",
        "ruten_code": "0019000200020001",
        "model": "雷霆 S150 RACINGS",
        "tag": "#8257",
        "condition": "檢查和更換耗材，確保車輛運作順暢",
        "mileage": "61,XXX km",
        "images": [
            "https://cdn.store-assets.com/s/1336053/i/79244174.jpeg",
            "https://cdn.store-assets.com/s/1336053/i/79244176.jpeg",
            "https://cdn.store-assets.com/s/1336053/i/79244173.jpeg",
            "https://cdn.store-assets.com/s/1336053/i/79244175.jpeg",
            "https://cdn.store-assets.com/s/1336053/i/79244172.jpeg"
        ],
        "price": "4800000",
        "warranty": true
    }
]